{
  "project_info": {
    "project_number": "795075128601",
    "project_id": "ecore-850e9",
    "storage_bucket": "ecore-850e9.appspot.com"
  },
  "client": [
    {
      "client_info": {
        "mobilesdk_app_id": "1:795075128601:android:bfb3f37f6e90c7c525e988",
        "android_client_info": {
          "package_name": "com.example.ecore"
        }
      },
      "oauth_client": [],
      "api_key": [
        {
          "current_key": "AIzaSyAdU_3p8BrSQfU7_OEz7SfxFbAu7ZGjQo4"
        }
      ],
      "services": {
        "appinvite_service": {
          "other_platform_oauth_client": []
        }
      }
    }
  ],
  "configuration_version": "1"
}